{
  "-Ouuhjh9ooN83G_kkzLs": {
    "doMat": "Mật",
    "fileData": "(Đã lưu trữ cục bộ bảo mật trên Firebase)",
    "fileName": "CV công ty truyền thông Bee_0001 (1).pdf",
    "kyHieuMat": "C",
    "nam": "2026",
    "ngayKy": "10/06/2026",
    "ngayNhan": "12/06/2026",
    "nguoiKy": "Trần Văn Chính",
    "nguoiNhan": "Văn Hoài Thanh",
    "noiBanHanh": "Sở y tế",
    "noiDung": "szdfgsdfgsdfg",
    "soCongVan": "12/BC",
    "soMat": "001",
    "soTo": "2",
    "tenVanBan": "Báo cáo",
    "timestamp": 1781249772506
  }
}